{
	"$schema": "https://unpkg.com/release-it/schema/release-it.json",
	"git": {
		"commitMessage": "chore(release): v${version} [skip ci]",
		"requireBranch": "master",
		"requireCleanWorkingDir": true,
		"tagName": "v${version}"
	},
	"github": {
		"release": true,
		"tokenRef": "GITHUB_TOKEN"
	},
	"hooks": {
		"after:bump": "npx auto-changelog -p",
		"after:release": "echo 🟢 Successfully released ${name} v${version} to ${repo.repository}.",
		"before:init": ["git pull", "pnpm lint-fix", "pnpm test"]
	},
	"plugins": {
		"release-it-pnpm": {}
	}
}
